[{"JerseyNumber":"11","Height":"6-1","Weight":"199 lbs","Shoots":"L","DateOfBirth":"1989/03/17","BirthPlace":"Vasteras, Sweden","Draft":"2007","CurrentTeam":null,"PositionAcronym":"Center","SeoId":"mikael-backlund","FirstName":"Mikael","LastName":"Backlund","Image":null},{"JerseyNumber":"44","Height":"6-1","Weight":"196 lbs","Shoots":"L","DateOfBirth":"1988/06/04","BirthPlace":"Pittsburgh, Pennsylvania, United States","Draft":"2008","CurrentTeam":null,"PositionAcronym":"Defense","SeoId":"matt-bartkowski","FirstName":"Matt","LastName":"Bartkowski","Image":null},{"JerseyNumber":"93","Height":"6-1","Weight":"200 lbs","Shoots":"L","DateOfBirth":"1996/06/20","BirthPlace":"Holland Landing, Ontario, Canada","Draft":"2014","CurrentTeam":null,"PositionAcronym":"Left Wing","SeoId":"sam-bennett","FirstName":"Sam","LastName":"Bennett","Image":null},{"JerseyNumber":"7","Height":"6-1","Weight":"182 lbs","Shoots":"L","DateOfBirth":"1990/06/07","BirthPlace":"Chatham, Ontario, Canada","Draft":"2008","CurrentTeam":null,"PositionAcronym":"Defense","SeoId":"tj-brodie","FirstName":"T.J.","LastName":"Brodie","Image":null},{"JerseyNumber":"36","Height":"6-3","Weight":"215 lbs","Shoots":"R","DateOfBirth":"1985/08/17","BirthPlace":"Vancouver, British Columbia, Canada","Draft":"2004","CurrentTeam":null,"PositionAcronym":"Right Wing","SeoId":"troy-brouwer","FirstName":"Troy","LastName":"Brouwer","Image":null},{"JerseyNumber":"79","Height":"6-2","Weight":"208 lbs","Shoots":"L","DateOfBirth":"1992/04/20","BirthPlace":"Swan River, Manitoba, Canada","Draft":"2010","CurrentTeam":null,"PositionAcronym":"Right Wing","SeoId":"micheal-ferland","FirstName":"Micheal","LastName":"Ferland","Image":null},{"JerseyNumber":"67","Height":"6-1","Weight":"194 lbs","Shoots":"L","DateOfBirth":"1988/02/17","BirthPlace":"Kladno, Czechoslovakia","Draft":"2006","CurrentTeam":null,"PositionAcronym":"Right Wing","SeoId":"michael-frolik","FirstName":"Michael","LastName":"Frolik","Image":null},{"JerseyNumber":"13","Height":"5-9","Weight":"157 lbs","Shoots":"L","DateOfBirth":"1993/08/13","BirthPlace":"Salem, New Jersey, United States","Draft":"2011","CurrentTeam":null,"PositionAcronym":"Left Wing","SeoId":"johnny-gaudreau","FirstName":"Johnny","LastName":"Gaudreau","Image":null},{"JerseyNumber":"5","Height":"6-0","Weight":"198 lbs","Shoots":"L","DateOfBirth":"1983/10/03","BirthPlace":"Toronto, Ontario, Canada","Draft":"-","CurrentTeam":null,"PositionAcronym":"Defense","SeoId":"mark-giordano","FirstName":"Mark","LastName":"Giordano","Image":null},{"JerseyNumber":"15","Height":"6-1","Weight":"213 lbs","Shoots":"L","DateOfBirth":"1983/11/29","BirthPlace":"Regina, Saskatchewan, Canada","Draft":"2003","CurrentTeam":null,"PositionAcronym":"Left Wing","SeoId":"tanner-glass","FirstName":"Tanner","LastName":"Glass","Image":null},{"JerseyNumber":"27","Height":"6-6","Weight":"210 lbs","Shoots":"R","DateOfBirth":"1993/06/17","BirthPlace":"Toronto, Ontario, Canada","Draft":"2011","CurrentTeam":null,"PositionAcronym":"Defense","SeoId":"dougie-hamilton","FirstName":"Dougie","LastName":"Hamilton","Image":null},{"JerseyNumber":"24","Height":"6-2","Weight":"205 lbs","Shoots":"R","DateOfBirth":"1990/08/16","BirthPlace":"St. Malo, Manitoba, Canada","Draft":"2008","CurrentTeam":null,"PositionAcronym":"Defense","SeoId":"travis-hamonic","FirstName":"Travis","LastName":"Hamonic","Image":null},{"JerseyNumber":"21","Height":"6-2","Weight":"208 lbs","Shoots":"R","DateOfBirth":"1991/11/23","BirthPlace":"Kennebunkport, Maine, United States","Draft":"-","CurrentTeam":null,"PositionAcronym":"Right Wing","SeoId":"garnet-hathaway","FirstName":"Garnet","LastName":"Hathaway","Image":null},{"JerseyNumber":"46","Height":"6-2","Weight":"197 lbs","Shoots":"R","DateOfBirth":"1991/08/28","BirthPlace":"Cadca, Czechoslovakia","Draft":"-","CurrentTeam":null,"PositionAcronym":"Left Wing","SeoId":"marek-hrivik","FirstName":"Marek","LastName":"Hrivik","Image":null},{"JerseyNumber":"77","Height":"6-4","Weight":"202 lbs","Shoots":"L","DateOfBirth":"1994/09/13","BirthPlace":"Hamilton, Ontario, Canada","Draft":"2012","CurrentTeam":null,"PositionAcronym":"Center","SeoId":"mark-jankowski","FirstName":"Mark","LastName":"Jankowski","Image":null},{"JerseyNumber":"61","Height":"6-2","Weight":"187 lbs","Shoots":"L","DateOfBirth":"1994/01/06","BirthPlace":"Edmonton, Alberta, Canada","Draft":"2012","CurrentTeam":null,"PositionAcronym":"Defense","SeoId":"brett-kulak","FirstName":"Brett","LastName":"Kulak","Image":null},{"JerseyNumber":"20","Height":"6-0","Weight":"209 lbs","Shoots":"R","DateOfBirth":"1995/02/02","BirthPlace":"Salmon Arm, British Columbia, Canada","Draft":"2013","CurrentTeam":null,"PositionAcronym":"Right Wing","SeoId":"curtis-lazar","FirstName":"Curtis","LastName":"Lazar","Image":null},{"JerseyNumber":"23","Height":"6-3","Weight":"195 lbs","Shoots":"L","DateOfBirth":"1994/10/12","BirthPlace":"Brampton, Ontario, Canada","Draft":"2013","CurrentTeam":null,"PositionAcronym":"Center","SeoId":"sean-monahan","FirstName":"Sean","LastName":"Monahan","Image":null},{"JerseyNumber":"25","Height":"6-1","Weight":"195 lbs","Shoots":"R","DateOfBirth":"1992/09/26","BirthPlace":"Denver, Colorado, United States","Draft":"2011","CurrentTeam":null,"PositionAcronym":"Center","SeoId":"nick-shore","FirstName":"Nick","LastName":"Shore","Image":null},{"JerseyNumber":"41","Height":"6-4","Weight":"215 lbs","Shoots":"L","DateOfBirth":"1982/03/22","BirthPlace":"Kingston, Ontario, Canada","Draft":"2001","CurrentTeam":null,"PositionAcronym":"Goaltender","SeoId":"mike-smith","FirstName":"Mike","LastName":"Smith","Image":null},{"JerseyNumber":"18","Height":"6-1","Weight":"195 lbs","Shoots":"L","DateOfBirth":"1983/12/19","BirthPlace":"Mississauga, Ontario, Canada","Draft":"2002","CurrentTeam":null,"PositionAcronym":"Center","SeoId":"matt-stajan","FirstName":"Matt","LastName":"Stajan","Image":null},{"JerseyNumber":"8","Height":"6-2","Weight":"242 lbs","Shoots":"R","DateOfBirth":"1987/10/30","BirthPlace":"Toronto, Ontario, Canada","Draft":"2006","CurrentTeam":null,"PositionAcronym":"Right Wing","SeoId":"chris-stewart-40940","FirstName":"Chris","LastName":"Stewart","Image":null},{"JerseyNumber":"26","Height":"6-3","Weight":"210 lbs","Shoots":"R","DateOfBirth":"1990/06/07","BirthPlace":"Winnipeg, Manitoba, Canada","Draft":"2008","CurrentTeam":null,"PositionAcronym":"Defense","SeoId":"michael-stone","FirstName":"Michael","LastName":"Stone","Image":null},{"JerseyNumber":"19","Height":"6-2","Weight":"202 lbs","Shoots":"L","DateOfBirth":"1997/12/11","BirthPlace":"Scottsdale, Arizona, United States","Draft":"2016","CurrentTeam":null,"PositionAcronym":"Left Wing","SeoId":"matthew-tkachuk","FirstName":"Matthew","LastName":"Tkachuk","Image":null},{"JerseyNumber":"10","Height":"5-11","Weight":"176 lbs","Shoots":"R","DateOfBirth":"1986/05/13","BirthPlace":"Lethbridge, Alberta, Canada","Draft":"2004","CurrentTeam":null,"PositionAcronym":"Left Wing","SeoId":"kris-versteeg","FirstName":"Kris","LastName":"Versteeg","Image":null}]
